fly_python_sdk/__init__.py
fly_python_sdk/exceptions.py
fly_python_sdk/fly/__init__.py
fly_python_sdk/fly/api.py
fly_python_sdk/fly/app.py
fly_python_sdk/fly/machine.py
fly_python_sdk/fly/org.py
fly_python_sdk/fly/volume.py
fly_python_sdk/models/__init__.py
fly_python_sdk/models/app.py
fly_python_sdk/models/machine.py
fly_python_sdk/models/org.py
fly_python_sdk/models/volume.py
fly_python_sdk-0.3.4.dist-info/LICENSE
fly_python_sdk-0.3.4.dist-info/METADATA
fly_python_sdk-0.3.4.dist-info/WHEEL
fly_python_sdk-0.3.4.dist-info/RECORD
