Metadata-Version: 2.1
Name: fly-python-sdk
Version: 0.3.4
Summary: 
Author: Brian Li
Author-email: brian@brianli.com
Requires-Python: >=3.11,<4.0
Classifier: Programming Language :: Python :: 3
Classifier: Programming Language :: Python :: 3.11
Requires-Dist: httpx (>=0.24.1,<0.25.0)
Requires-Dist: pydantic (>=2.0.2,<3.0.0)
